theknot/__init__.py
theknot/cli.py
theknot/exceptions.py
theknot-0.0.1.dist-info/LICENSE
theknot-0.0.1.dist-info/METADATA
theknot-0.0.1.dist-info/WHEEL
theknot-0.0.1.dist-info/entry_points.txt
theknot-0.0.1.dist-info/top_level.txt
theknot-0.0.1.dist-info/RECORD
